setup.py
pyomni/__init__.py
pyomni/omni_task.py
pyomni/pyomni.py
pyomni/util.py
pyomni.egg-info/PKG-INFO
pyomni.egg-info/SOURCES.txt
pyomni.egg-info/dependency_links.txt
pyomni.egg-info/top_level.txt
pyomni/webdav/Condition.py
pyomni/webdav/Connection.py
pyomni/webdav/Constants.py
pyomni/webdav/NameCheck.py
pyomni/webdav/Utils.py
pyomni/webdav/VersionHandler.py
pyomni/webdav/WebdavClient.py
pyomni/webdav/WebdavRequests.py
pyomni/webdav/WebdavResponse.py
pyomni/webdav/__init__.py
pyomni/webdav/davlib.py
pyomni/webdav/logger.py
pyomni/webdav/qp_xml.py
pyomni/webdav/acp/Ace.py
pyomni/webdav/acp/AceHandler.py
pyomni/webdav/acp/Acl.py
pyomni/webdav/acp/GrantDeny.py
pyomni/webdav/acp/Principal.py
pyomni/webdav/acp/Privilege.py
pyomni/webdav/acp/__init__.py