Metadata-Version: 1.1
Name: pyomni
Version: 0.1.6.1
Summary: Python library to handle omnifocus tasks.
Home-page: https://github.com/taxpon/pyomni/blob/master/pyomni/pyomni.py
Author: Takuro Wada
Author-email: taxpon@gmail.com
License: MIT
Platform: UNKNOWN
Classifier: License :: OSI Approved :: MIT License
Classifier: Programming Language :: Python
